pytest_darker.py
pytest_darker-0.1.4.dist-info/LICENSE.rst
pytest_darker-0.1.4.dist-info/METADATA
pytest_darker-0.1.4.dist-info/WHEEL
pytest_darker-0.1.4.dist-info/entry_points.txt
pytest_darker-0.1.4.dist-info/top_level.txt
pytest_darker-0.1.4.dist-info/RECORD
