Metadata-Version: 2.1
Name: pytest_darker
Version: 0.1.4
Summary: A pytest plugin for checking of modified code using Darker
Home-page: https://github.com/akaihola/pytest_darker
Author: Antti Kaihola
Author-email: 13725+akaihola@users.noreply.github.com
License: BSD
Project-URL: Source Code, https://github.com/akaihola/pytest_darker
Project-URL: Change Log, https://github.com/akaihola/pytest_darker/CHANGES.rst
Classifier: Programming Language :: Python :: 3 :: Only
Classifier: Programming Language :: Python :: 3.6
Classifier: Programming Language :: Python :: 3.7
Classifier: Programming Language :: Python :: 3.8
Requires-Python: >=3.6
License-File: LICENSE.rst
Requires-Dist: darker >=1.1.0
Requires-Dist: pytest <7,>=6.0.1
Requires-Dist: typing-extensions ; python_version < "3.8"
Provides-Extra: test
Requires-Dist: mypy >=0.782 ; extra == 'test'
Requires-Dist: pytest-black ; extra == 'test'
Requires-Dist: pytest-isort >=1.1.0 ; extra == 'test'
Requires-Dist: pytest-mypy ; extra == 'test'
